mkdocs_markupsafe_markdown_filter/__init__.py
mkdocs_markupsafe_markdown_filter/__version__.py
mkdocs_markupsafe_markdown_filter/plugin.py
mkdocs_markupsafe_markdown_filter-0.1.1.dist-info/METADATA
mkdocs_markupsafe_markdown_filter-0.1.1.dist-info/WHEEL
mkdocs_markupsafe_markdown_filter-0.1.1.dist-info/entry_points.txt
mkdocs_markupsafe_markdown_filter-0.1.1.dist-info/licenses/LICENSE
mkdocs_markupsafe_markdown_filter-0.1.1.dist-info/RECORD
