Metadata-Version: 2.4
Name: mkdocs-markupsafe-markdown-filter
Version: 0.1.1
Summary: A MkDocs plugin to add a markdown filter to jinja templates.
Project-URL: Source, https://github.com/ntno/mkdocs-markupsafe-markdown-filter
Project-URL: Issues, https://github.com/ntno/mkdocs-markupsafe-markdown-filter/issues
Author-email: Byrne Reese <byrne@majordojo.com>, Natan Organick <markupsafe.markdown.filter@gmail.com>
Maintainer: Natan Organick
License-Expression: MIT
License-File: LICENSE
Keywords: jinja,mkdocs
Classifier: Development Status :: 4 - Beta
Classifier: Environment :: Web Environment
Classifier: Intended Audience :: Developers
Classifier: Intended Audience :: Information Technology
Classifier: License :: OSI Approved :: MIT License
Classifier: Programming Language :: Python
Classifier: Programming Language :: Python :: 3 :: Only
Classifier: Programming Language :: Python :: 3.8
Classifier: Programming Language :: Python :: 3.9
Classifier: Programming Language :: Python :: 3.10
Classifier: Programming Language :: Python :: 3.11
Classifier: Programming Language :: Python :: 3.12
Classifier: Topic :: Documentation
Classifier: Topic :: Software Development :: Documentation
Classifier: Topic :: Text Processing :: Markup :: HTML
Requires-Python: >=3.8
Requires-Dist: markupsafe
Requires-Dist: mkdocs
